tests/__init__.py
tests/conftest.py
tests/test_1_views.py
tests/test_ActionType_ModelStatus.py
tests/test_ObjListField.py
tests/test_embedded_sources.py
tests/test_fields.py
tests/test_json_load.py
tests/test_membs_cards.py
tests/Tutorial/__init__.py
tests/Tutorial/test_tutorial.py
tests/Tutorial/view_models.py
tests/example_views/__init__.py
tests/example_views/cardView.py
tests/example_views/memberView.py
tests/test_datetime/__init__.py
tests/test_datetime/test_vmdatetime.py
viewmodel/__init__.py
viewmodel/auth.py
viewmodel/dbCopyier.py
viewmodel/json_load.py
viewmodel/viewFields.py
viewmodel/viewModel.py
viewmodel/viewMongoDB.py
viewmodel/viewMongoSources.py
viewmodel/viewSources.py
viewmodel/vmdatetime.py
XType-0.3.7.dist-info/METADATA
XType-0.3.7.dist-info/WHEEL
XType-0.3.7.dist-info/entry_points.txt
XType-0.3.7.dist-info/top_level.txt
XType-0.3.7.dist-info/RECORD
