Metadata-Version: 2.1
Name: XType
Version: 0.3.7
Summary: Model and View support for bottle framework, currently supports MongoDB. The ViewModel provides a high level DB schema and interface to a database as well as an interface from the DB to views. Current version works with bottle framework and pymongo however a previous version supported SQLAlchemy and other frameworks could be supported.
Home-page: https://bitbucket.org/objdict/viewmodel
Author: Ian Ogilvy
Author-email: support@salect.nz
License: LGPL
Keywords: database bottle mongodb pymongo view mvc model
Platform: UNKNOWN
Classifier: Development Status :: 4 - Beta
Classifier: Intended Audience :: Developers
Classifier: Topic :: Software Development :: Libraries :: Python Modules
Classifier: Topic :: Utilities
Classifier: License :: OSI Approved :: GNU Library or Lesser General Public License (LGPL)
Classifier: Operating System :: OS Independent
Classifier: Programming Language :: Python :: 3
Classifier: Programming Language :: Python :: 3.2
Classifier: Programming Language :: Python :: 3.3
Classifier: Programming Language :: Python :: 3.4
Classifier: Programming Language :: Python :: 3.5
Classifier: Programming Language :: Python :: 3.6
Requires-Dist: objdict
Requires-Dist: pymongo
Requires-Dist: bottle
Requires-Dist: mako
